setup.cfg
setup.py
gfirefly/__init__.py
gfirefly.egg-info/PKG-INFO
gfirefly.egg-info/SOURCES.txt
gfirefly.egg-info/dependency_links.txt
gfirefly.egg-info/entry_points.txt
gfirefly.egg-info/not-zip-safe
gfirefly.egg-info/requires.txt
gfirefly.egg-info/top_level.txt
gfirefly/dbentrust/__init__.py
gfirefly/dbentrust/dbpool.py
gfirefly/dbentrust/madminanager.py
gfirefly/dbentrust/memclient.py
gfirefly/dbentrust/memfields.py
gfirefly/dbentrust/memmodel.py
gfirefly/dbentrust/memobject.py
gfirefly/dbentrust/mmode.py
gfirefly/dbentrust/util.py
gfirefly/distributed/__init__.py
gfirefly/distributed/child.py
gfirefly/distributed/manager.py
gfirefly/distributed/node.py
gfirefly/distributed/reference.py
gfirefly/distributed/root.py
gfirefly/management/__init__.py
gfirefly/management/commands/__init__.py
gfirefly/management/commands/createproject.py
gfirefly/management/commands/reloadmodule.py
gfirefly/management/commands/stopservice.py
gfirefly/master/__init__.py
gfirefly/master/master.py
gfirefly/master/rootapp.py
gfirefly/master/webapp.py
gfirefly/netconnect/__init__.py
gfirefly/netconnect/connection.py
gfirefly/netconnect/datapack.py
gfirefly/netconnect/manager.py
gfirefly/netconnect/protoc.py
gfirefly/script/__init__.py
gfirefly/script/gfirefly-admin.py
gfirefly/server/__init__.py
gfirefly/server/admin.py
gfirefly/server/globalobject.py
gfirefly/server/logobj.py
gfirefly/server/server.py
gfirefly/test/__init__.py
gfirefly/test/dbentrust_test.py
gfirefly/test/memmodel_test.py
gfirefly/test/test_distributed_node.py
gfirefly/test/test_distributed_root.py
gfirefly/test/test_netconnect_client.py
gfirefly/test/test_netconnect_server.py
gfirefly/test/test_server_apptest.py
gfirefly/test/test_server_main.py
gfirefly/test/test_server_master.py
gfirefly/utils/__init__.py
gfirefly/utils/interfaces.py
gfirefly/utils/services.py
gfirefly/utils/singleton.py
gfirefly/utils/version.py