Metadata-Version: 1.0
Name: gfirefly
Version: 0.1.9alpha
Summary: Achieve firefly based on gtwisted
Home-page: http://www.9miao.com/
Author: lanjinmin
Author-email: zhuiming.mu@gmail.com
License: MIT
Keywords: gevent gtwisted pb firefly gevent
Platform: UNKNOWN
